ida_domain/__init__.py
ida_domain/base.py
ida_domain/bytes.py
ida_domain/comments.py
ida_domain/database.py
ida_domain/entries.py
ida_domain/flowchart.py
ida_domain/functions.py
ida_domain/heads.py
ida_domain/hooks.py
ida_domain/imports.py
ida_domain/instructions.py
ida_domain/names.py
ida_domain/operands.py
ida_domain/py.typed
ida_domain/segments.py
ida_domain/signature_files.py
ida_domain/strings.py
ida_domain/types.py
ida_domain/xrefs.py
ida_domain-0.4.0.dist-info/licenses/LICENSE
ida_domain-0.4.0.dist-info/METADATA
ida_domain-0.4.0.dist-info/WHEEL
ida_domain-0.4.0.dist-info/top_level.txt
ida_domain-0.4.0.dist-info/RECORD
