Metadata-Version: 2.4
Name: ida-domain
Version: 0.4.0
Summary: IDA Domain API - Python interface for IDA Pro reverse engineering platform
Author-email: Hex-Rays SA <support@hex-rays.com>
License-Expression: MIT
Project-URL: Homepage, https://hex-rays.com/
Project-URL: Documentation, https://ida-domain.docs.hex-rays.com/
Project-URL: Repository, https://github.com/hexrayssa/ida-domain
Project-URL: Issues, https://github.com/hexrayssa/ida-domain/issues
Keywords: ida,ida-pro,reverse-engineering,disassembler,binary-analysis,malware-analysis,security
Classifier: Programming Language :: Python :: 3
Classifier: Programming Language :: Python :: 3.9
Classifier: Programming Language :: Python :: 3.10
Classifier: Programming Language :: Python :: 3.11
Classifier: Programming Language :: Python :: 3.12
Classifier: Programming Language :: Python :: 3.13
Requires-Python: >=3.9
License-File: LICENSE
Requires-Dist: idapro>=0.0.5
Requires-Dist: typing-extensions>=4.14.0
Provides-Extra: dev
Requires-Dist: pytest>=7.0.0; extra == "dev"
Requires-Dist: pytest-cov>=4.0.0; extra == "dev"
Requires-Dist: graphviz>=0.20.0; extra == "dev"
Requires-Dist: python-semantic-release>=10.3.1; extra == "dev"
Provides-Extra: docs
Requires-Dist: mkdocs-material; extra == "docs"
Requires-Dist: mkdocs-click>=0.9.0; extra == "docs"
Requires-Dist: mkdocstrings[python]>=0.28.0; extra == "docs"
Requires-Dist: mkdocs-gen-files>=0.5.0; extra == "docs"
Requires-Dist: mkdocs-include-markdown-plugin>=7.1.5; extra == "docs"
Requires-Dist: mkdocs-literate-nav>=0.6.2; extra == "docs"
Requires-Dist: mkdocs-section-index>=0.3.10; extra == "docs"
Requires-Dist: mkdocs-llmstxt>=0.2.0; extra == "docs"
Dynamic: license-file
